h2h_galleryinfo_parser/__init__.py
h2h_galleryinfo_parser/gallery_url_parser.py
h2h_galleryinfo_parser/galleryinfo_parser.py
h2h_galleryinfo_parser/py.typed
h2h_galleryinfo_parser-0.2.2.dist-info/LICENSE
h2h_galleryinfo_parser-0.2.2.dist-info/METADATA
h2h_galleryinfo_parser-0.2.2.dist-info/WHEEL
h2h_galleryinfo_parser-0.2.2.dist-info/top_level.txt
h2h_galleryinfo_parser-0.2.2.dist-info/RECORD
