Metadata-Version: 2.1
Name: h2h-galleryinfo-parser
Version: 0.2.2
Summary: A simple H@H GalleryInfo Parser
Author: Kuan-Lun Wang
License: GNU Affero General Public License v3
Project-URL: Homepage, https://github.com/Kuan-Lun/h2h-galleryinfo-parser
Project-URL: Source, https://github.com/Kuan-Lun/h2h-galleryinfo-parser
Project-URL: Tracker, https://github.com/Kuan-Lun/h2h-galleryinfo-parser/issues
Classifier: Development Status :: 3 - Alpha
Classifier: Intended Audience :: Developers
Classifier: Operating System :: OS Independent
Classifier: License :: OSI Approved :: GNU Affero General Public License v3 or later (AGPLv3+)
Classifier: Programming Language :: Python :: 3.13
License-File: LICENSE
